aedev/pythonanywhere.py
aedev_pythonanywhere-0.3.7.dist-info/LICENSE.md
aedev_pythonanywhere-0.3.7.dist-info/METADATA
aedev_pythonanywhere-0.3.7.dist-info/WHEEL
aedev_pythonanywhere-0.3.7.dist-info/top_level.txt
aedev_pythonanywhere-0.3.7.dist-info/zip-safe
aedev_pythonanywhere-0.3.7.dist-info/RECORD
